[
    {
        "словоформа": "транслитерированного",
        "контекст": "В знаменитой работе Ильи Смирнова Либерастия рассматривается модный ныне в России американский учебник «Экономикс» (его название выглядит именно так — в виде транслитерированного, а не переведенного английского слова, поскольку никто не смеет посягать ни на одну букву каноноческого либерального вероучения).",
        "лемма": "транслитерировать",
        "грамматика": "глагол, родительный, средний, причастие, страдательный, совершенный, полная форма, прошедшее, единственное, переходный",
        "синтаксические признаки": "атрибутивная клауза, распространенный причастный оборот, именная клауза, есть зависимые"
    }
]